{
  "annotations": {
    "list": [
      {
        "builtIn": 1,
        "datasource": { "type": "grafana", "uid": "-- Grafana --" },
        "enable": true,
        "hide": true,
        "iconColor": "rgba(0, 211, 255, 1)",
        "name": "Annotations & Alerts",
        "type": "dashboard"
      }
    ]
  },
  "editable": true,
  "fiscalYearStartMonth": 0,
  "graphTooltip": 1,
  "id": null,
  "links": [],
  "liveNow": false,
  "panels": [
    {
      "collapsed": false,
      "gridPos": { "h": 1, "w": 24, "x": 0, "y": 0 },
      "id": 1,
      "panels": [],
      "title": "🎯 Key Metrics",
      "type": "row"
    },
    {
      "datasource": { "type": "prometheus", "uid": "prometheus" },
      "fieldConfig": {
        "defaults": {
          "color": { "mode": "thresholds" },
          "mappings": [],
          "thresholds": {
            "mode": "absolute",
            "steps": [
              { "color": "green", "value": null },
              { "color": "yellow", "value": 10 },
              { "color": "red", "value": 50 }
            ]
          },
          "unit": "short"
        }
      },
      "gridPos": { "h": 4, "w": 4, "x": 0, "y": 1 },
      "id": 2,
      "options": {
        "colorMode": "background",
        "graphMode": "area",
        "justifyMode": "auto",
        "orientation": "auto",
        "reduceOptions": { "calcs": ["lastNotNull"], "fields": "", "values": false },
        "textMode": "auto"
      },
      "title": "Active Executions",
      "targets": [
        { "expr": "imgd_engine_executions_active", "legendFormat": "Active", "refId": "A" }
      ],
      "type": "stat"
    },
    {
      "datasource": { "type": "prometheus", "uid": "prometheus" },
      "fieldConfig": {
        "defaults": {
          "color": { "mode": "thresholds" },
          "mappings": [],
          "thresholds": {
            "mode": "absolute",
            "steps": [
              { "color": "blue", "value": null },
              { "color": "yellow", "value": 20 }
            ]
          }
        }
      },
      "gridPos": { "h": 4, "w": 4, "x": 4, "y": 1 },
      "id": 3,
      "options": { "colorMode": "background", "graphMode": "area", "reduceOptions": { "calcs": ["lastNotNull"] } },
      "title": "Pending Executions",
      "targets": [
        { "expr": "imgd_engine_executions_pending", "refId": "A" }
      ],
      "type": "stat"
    },
    {
      "datasource": { "type": "prometheus", "uid": "prometheus" },
      "fieldConfig": {
        "defaults": {
          "color": { "mode": "thresholds" },
          "mappings": [],
          "thresholds": {
            "mode": "absolute",
            "steps": [
              { "color": "green", "value": null },
              { "color": "yellow", "value": 0.01 },
              { "color": "red", "value": 0.05 }
            ]
          },
          "unit": "percentunit"
        }
      },
      "gridPos": { "h": 4, "w": 4, "x": 8, "y": 1 },
      "id": 4,
      "options": { "colorMode": "value", "graphMode": "area", "reduceOptions": { "calcs": ["lastNotNull"] } },
      "title": "Error Rate (5m)",
      "targets": [
        {
          "expr": "sum(rate(imgd_engine_execution_total{status=\"failed\"}[$__rate_interval])) / sum(rate(imgd_engine_execution_total[$__rate_interval]))",
          "refId": "A"
        }
      ],
      "type": "stat"
    },
    {
      "datasource": { "type": "prometheus", "uid": "prometheus" },
      "fieldConfig": {
        "defaults": {
          "color": { "mode": "thresholds" },
          "thresholds": {
            "mode": "absolute",
            "steps": [
              { "color": "green", "value": null },
              { "color": "yellow", "value": 5000 },
              { "color": "red", "value": 30000 }
            ]
          },
          "unit": "ms"
        }
      },
      "gridPos": { "h": 4, "w": 4, "x": 12, "y": 1 },
      "id": 5,
      "options": { "colorMode": "value", "graphMode": "area", "reduceOptions": { "calcs": ["lastNotNull"] } },
      "title": "Execution p95",
      "targets": [
        {
          "expr": "histogram_quantile(0.95, sum(rate(imgd_engine_execution_duration_milliseconds_bucket[$__rate_interval])) by (le))",
          "refId": "A"
        }
      ],
      "type": "stat"
    },
    {
      "datasource": { "type": "prometheus", "uid": "prometheus" },
      "fieldConfig": {
        "defaults": {
          "color": { "mode": "thresholds" },
          "thresholds": {
            "mode": "absolute",
            "steps": [
              { "color": "green", "value": null },
              { "color": "orange", "value": 1 }
            ]
          }
        }
      },
      "gridPos": { "h": 4, "w": 4, "x": 16, "y": 1 },
      "id": 6,
      "options": { "colorMode": "background", "graphMode": "area", "reduceOptions": { "calcs": ["lastNotNull"] } },
      "title": "Running Nodes",
      "targets": [
        { "expr": "imgd_engine_nodes_running", "refId": "A" }
      ],
      "type": "stat"
    },
    {
      "datasource": { "type": "prometheus", "uid": "prometheus" },
      "fieldConfig": {
        "defaults": {
          "unit": "short"
        }
      },
      "gridPos": { "h": 4, "w": 4, "x": 20, "y": 1 },
      "id": 7,
      "options": { "colorMode": "value", "graphMode": "area", "reduceOptions": { "calcs": ["lastNotNull"] } },
      "title": "Retries (5m)",
      "targets": [
        { "expr": "sum(increase(imgd_engine_node_retry_total[$__rate_interval]))", "refId": "A" }
      ],
      "type": "stat"
    },
    {
      "collapsed": false,
      "gridPos": { "h": 1, "w": 24, "x": 0, "y": 5 },
      "id": 10,
      "panels": [],
      "title": "📊 Execution Metrics",
      "type": "row"
    },
    {
      "datasource": { "type": "prometheus", "uid": "prometheus" },
      "fieldConfig": {
        "defaults": {
          "color": { "mode": "palette-classic" },
          "custom": {
            "drawStyle": "line",
            "fillOpacity": 20,
            "lineInterpolation": "smooth",
            "lineWidth": 2,
            "stacking": { "mode": "none" }
          },
          "unit": "short"
        }
      },
      "gridPos": { "h": 8, "w": 12, "x": 0, "y": 6 },
      "id": 11,
      "options": {
        "legend": { "calcs": ["mean", "max", "sum"], "displayMode": "table", "placement": "bottom" },
        "tooltip": { "mode": "multi", "sort": "desc" }
      },
      "targets": [
        {
          "expr": "sum(rate(imgd_engine_execution_total[$__rate_interval])) by (status)",
          "legendFormat": "{{status}}",
          "refId": "A"
        }
      ],
      "title": "Execution Rate by Status",
      "type": "timeseries"
    },
    {
      "datasource": { "type": "prometheus", "uid": "prometheus" },
      "fieldConfig": {
        "defaults": {
          "color": { "mode": "palette-classic" },
          "custom": {
            "drawStyle": "line",
            "fillOpacity": 10,
            "lineWidth": 2
          },
          "unit": "ms"
        }
      },
      "gridPos": { "h": 8, "w": 12, "x": 12, "y": 6 },
      "id": 12,
      "options": {
        "legend": { "calcs": ["mean", "max"], "displayMode": "table", "placement": "bottom" }
      },
      "targets": [
        {
          "expr": "histogram_quantile(0.50, sum(rate(imgd_engine_execution_duration_milliseconds_bucket[$__rate_interval])) by (le))",
          "legendFormat": "p50",
          "refId": "A"
        },
        {
          "expr": "histogram_quantile(0.90, sum(rate(imgd_engine_execution_duration_milliseconds_bucket[$__rate_interval])) by (le))",
          "legendFormat": "p90",
          "refId": "B"
        },
        {
          "expr": "histogram_quantile(0.99, sum(rate(imgd_engine_execution_duration_milliseconds_bucket[$__rate_interval])) by (le))",
          "legendFormat": "p99",
          "refId": "C"
        }
      ],
      "title": "Execution Duration Percentiles",
      "type": "timeseries"
    },
    {
      "collapsed": false,
      "gridPos": { "h": 1, "w": 24, "x": 0, "y": 14 },
      "id": 20,
      "panels": [],
      "title": "🔧 Node Metrics",
      "type": "row"
    },
    {
      "datasource": { "type": "prometheus", "uid": "prometheus" },
      "fieldConfig": {
        "defaults": {
          "color": { "mode": "palette-classic" },
          "custom": { "drawStyle": "line", "fillOpacity": 20, "lineWidth": 2, "stacking": { "mode": "normal" } }
        }
      },
      "gridPos": { "h": 8, "w": 12, "x": 0, "y": 15 },
      "id": 21,
      "options": {
        "legend": { "calcs": ["sum"], "displayMode": "table", "placement": "right" }
      },
      "targets": [
        {
          "expr": "sum(rate(imgd_engine_node_total[$__rate_interval])) by (node_type_id, status)",
          "legendFormat": "{{node_type_id}} - {{status}}",
          "refId": "A"
        }
      ],
      "title": "Node Executions by Type & Status",
      "type": "timeseries"
    },
    {
      "datasource": { "type": "prometheus", "uid": "prometheus" },
      "fieldConfig": {
        "defaults": {
          "custom": { "drawStyle": "line", "fillOpacity": 10, "lineWidth": 2 },
          "unit": "ms"
        }
      },
      "gridPos": { "h": 8, "w": 12, "x": 12, "y": 15 },
      "id": 22,
      "options": {
        "legend": { "calcs": ["mean", "max"], "displayMode": "table", "placement": "bottom" }
      },
      "targets": [
        {
          "expr": "histogram_quantile(0.95, sum(rate(imgd_engine_node_duration_milliseconds_bucket[$__rate_interval])) by (le, node_type_id))",
          "legendFormat": "{{node_type_id}}",
          "refId": "A"
        }
      ],
      "title": "Node Duration by Type (p95)",
      "type": "timeseries"
    },
    {
      "datasource": { "type": "prometheus", "uid": "prometheus" },
      "fieldConfig": {
        "defaults": {
          "custom": { "drawStyle": "line", "fillOpacity": 20, "lineWidth": 2 },
          "unit": "ms"
        }
      },
      "gridPos": { "h": 6, "w": 12, "x": 0, "y": 23 },
      "id": 23,
      "options": { "legend": { "displayMode": "list", "placement": "bottom" } },
      "targets": [
        {
          "expr": "histogram_quantile(0.95, sum(rate(imgd_engine_node_queue_time_milliseconds_bucket[$__rate_interval])) by (le))",
          "legendFormat": "Queue Time p95",
          "refId": "A"
        }
      ],
      "title": "Node Queue Wait Time",
      "type": "timeseries"
    },
    {
      "datasource": { "type": "prometheus", "uid": "prometheus" },
      "fieldConfig": {
        "defaults": {
          "custom": { "drawStyle": "bars", "fillOpacity": 80, "lineWidth": 1 }
        }
      },
      "gridPos": { "h": 6, "w": 12, "x": 12, "y": 23 },
      "id": 24,
      "targets": [
        {
          "expr": "sum(rate(imgd_engine_node_retry_total[$__rate_interval])) by (node_type_id)",
          "legendFormat": "{{node_type_id}}",
          "refId": "A"
        }
      ],
      "title": "Node Retries by Type",
      "type": "timeseries"
    },
    {
      "collapsed": false,
      "gridPos": { "h": 1, "w": 24, "x": 0, "y": 29 },
      "id": 30,
      "panels": [],
      "title": "⚡ Expression Performance",
      "type": "row"
    },
    {
      "datasource": { "type": "prometheus", "uid": "prometheus" },
      "fieldConfig": {
        "defaults": {
          "custom": { "drawStyle": "line", "fillOpacity": 10, "lineWidth": 2 },
          "unit": "µs"
        }
      },
      "gridPos": { "h": 6, "w": 12, "x": 0, "y": 30 },
      "id": 31,
      "targets": [
        {
          "expr": "histogram_quantile(0.95, sum(rate(imgd_engine_expression_duration_microseconds_bucket[$__rate_interval])) by (le, expression_type))",
          "legendFormat": "{{expression_type}} p95",
          "refId": "A"
        }
      ],
      "title": "Expression Evaluation Time",
      "type": "timeseries"
    },
    {
      "datasource": { "type": "prometheus", "uid": "prometheus" },
      "gridPos": { "h": 6, "w": 12, "x": 12, "y": 30 },
      "id": 32,
      "targets": [
        {
          "expr": "sum(rate(imgd_engine_expression_total[$__rate_interval])) by (expression_type, status)",
          "legendFormat": "{{expression_type}} - {{status}}",
          "refId": "A"
        }
      ],
      "title": "Expression Evaluations",
      "type": "timeseries"
    },
    {
      "collapsed": false,
      "gridPos": { "h": 1, "w": 24, "x": 0, "y": 36 },
      "id": 40,
      "panels": [],
      "title": "📝 Recent Logs",
      "type": "row"
    },
    {
      "datasource": { "type": "loki", "uid": "loki" },
      "gridPos": { "h": 10, "w": 24, "x": 0, "y": 37 },
      "id": 41,
      "options": {
        "dedupStrategy": "none",
        "enableLogDetails": true,
        "prettifyLogMessage": false,
        "showCommonLabels": false,
        "showLabels": true,
        "showTime": true,
        "sortOrder": "Descending",
        "wrapLogMessage": false
      },
      "targets": [
        {
          "expr": "{job=\"imgd\"} | json | event =~ \"execution.*|node.*\" | line_format \"[{{.level}}] {{.event}} execution={{.execution_id}} {{.message}}\"",
          "refId": "A"
        }
      ],
      "title": "Engine Events",
      "type": "logs"
    }
  ],
  "refresh": "10s",
  "schemaVersion": 39,
  "tags": ["imgd", "workflow", "engine"],
  "templating": {
    "list": [
      {
        "current": { "selected": false, "text": "All", "value": "$__all" },
        "datasource": { "type": "prometheus", "uid": "prometheus" },
        "definition": "label_values(imgd_engine_execution_total, workflow_id)",
        "hide": 0,
        "includeAll": true,
        "label": "Workflow",
        "multi": true,
        "name": "workflow_id",
        "query": "label_values(imgd_engine_execution_total, workflow_id)",
        "refresh": 2,
        "sort": 1,
        "type": "query"
      },
      {
        "current": { "selected": false, "text": "All", "value": "$__all" },
        "datasource": { "type": "prometheus", "uid": "prometheus" },
        "definition": "label_values(imgd_engine_node_total, node_type_id)",
        "hide": 0,
        "includeAll": true,
        "label": "Node Type",
        "multi": true,
        "name": "node_type_id",
        "query": "label_values(imgd_engine_node_total, node_type_id)",
        "refresh": 2,
        "sort": 1,
        "type": "query"
      }
    ]
  },
  "time": { "from": "now-1h", "to": "now" },
  "timepicker": {},
  "timezone": "",
  "title": "imgd - Workflow Engine",
  "uid": "imgd-engine-v2",
  "version": 1
}